jlod/__init__.py
jlod-2.0.1.dist-info/LICENSE
jlod-2.0.1.dist-info/METADATA
jlod-2.0.1.dist-info/WHEEL
jlod-2.0.1.dist-info/top_level.txt
jlod-2.0.1.dist-info/RECORD
