Metadata-Version: 2.1
Name: jlod
Version: 2.0.1
Summary: Local Document Oriented Database
Home-page: http://www.jlod.org
Author: WWW.JLOD.ORG
Author-email: contact@jload.org
License: UNKNOWN
Platform: UNKNOWN
Classifier: Programming Language :: Python :: 3
Classifier: License :: OSI Approved :: MIT License
Classifier: Operating System :: OS Independent
Requires-Python: >=3.6
